CHANGELOG.md
LICENSE
README.md
prompt_manager/__init__.py
prompt_manager/core/manager.py
prompt_manager/core/models.py
prompt_manager/core/protocols.py
prompt_manager/core/registry.py
prompt_manager/core/template.py
prompt_manager/exceptions.py
prompt_manager/integrations/__init__.py
prompt_manager/integrations/anthropic.py
prompt_manager/integrations/base.py
prompt_manager/integrations/langchain.py
prompt_manager/integrations/litellm.py
prompt_manager/integrations/openai.py
prompt_manager/integrations/types.py
prompt_manager/observability/__init__.py
prompt_manager/observability/logging.py
prompt_manager/observability/metrics.py
prompt_manager/observability/telemetry.py
prompt_manager/plugins/__init__.py
prompt_manager/plugins/anthropic_plugin.py
prompt_manager/plugins/base.py
prompt_manager/plugins/langchain_plugin.py
prompt_manager/plugins/litellm_plugin.py
prompt_manager/plugins/openai_plugin.py
prompt_manager/plugins/registry.py
prompt_manager/py.typed
prompt_manager/storage/__init__.py
prompt_manager/storage/file.py
prompt_manager/storage/memory.py
prompt_manager/storage/yaml_loader.py
prompt_manager/utils/__init__.py
prompt_manager/utils/async_helpers.py
prompt_manager/validation/__init__.py
prompt_manager/validation/loader.py
prompt_manager/validation/models.py
prompt_manager/validation/validators.py
prompt_manager/versioning/__init__.py
prompt_manager/versioning/store.py
agentic_prompt_manager-0.1.0b7.dist-info/LICENSE
agentic_prompt_manager-0.1.0b7.dist-info/METADATA
agentic_prompt_manager-0.1.0b7.dist-info/WHEEL
agentic_prompt_manager-0.1.0b7.dist-info/entry_points.txt
agentic_prompt_manager-0.1.0b7.dist-info/RECORD
