Metadata-Version: 2.1
Name: agentic-prompt-manager
Version: 0.1.0b7
Summary: Production-ready prompt management system with versioning, validation, and framework integrations for OpenAI, Anthropic, LangChain, and LiteLLM
Home-page: https://github.com/joshuamschultz/prompt-manager
License: MIT
Keywords: prompts,llm,ai,openai,anthropic,langchain,litellm,templating,pydantic,prompt-engineering
Author: Josh Schultz
Author-email: josh@example.com
Requires-Python: >=3.11,<4.0
Classifier: Development Status :: 4 - Beta
Classifier: Intended Audience :: Developers
Classifier: License :: OSI Approved :: MIT License
Classifier: Programming Language :: Python :: 3
Classifier: Programming Language :: Python :: 3.11
Classifier: Programming Language :: Python :: 3.12
Classifier: Programming Language :: Python :: 3 :: Only
Classifier: Topic :: Scientific/Engineering :: Artificial Intelligence
Classifier: Topic :: Software Development :: Libraries :: Python Modules
Classifier: Typing :: Typed
Provides-Extra: all
Provides-Extra: anthropic
Provides-Extra: langchain
Provides-Extra: litellm
Provides-Extra: openai
Requires-Dist: anthropic (>=0.42,<0.75) ; extra == "anthropic" or extra == "all"
Requires-Dist: langchain-core (>=0.3,<1.1) ; extra == "langchain" or extra == "all"
Requires-Dist: litellm (>=1.53.0,<2.0.0) ; extra == "litellm" or extra == "all"
Requires-Dist: openai (>=1.57,<3.0) ; extra == "openai" or extra == "all"
Requires-Dist: opentelemetry-api (>=1.28.2,<2.0.0)
Requires-Dist: opentelemetry-sdk (>=1.28.2,<2.0.0)
Requires-Dist: pybars4 (>=0.9.13,<0.10.0)
Requires-Dist: pydantic (>=2.10.0,<3.0.0)
Requires-Dist: pydantic-settings (>=2.6.0,<3.0.0)
Requires-Dist: python-dateutil (>=2.9.0,<3.0.0)
Requires-Dist: pyyaml (>=6.0.2,<7.0.0)
Requires-Dist: structlog (>=25.5.0,<26.0.0)
Requires-Dist: typing-extensions (>=4.12.0,<5.0.0)
Project-URL: Documentation, https://github.com/joshuamschultz/prompt-manager#readme
Project-URL: Repository, https://github.com/joshuamschultz/prompt-manager
